{
  "$schema": "../../../../schemas/recipe.schema.json",
  "name": "Silver Seas",
  "ingredients": [
    {
      "name": "Angostura bitters",
      "type": "bitter",
      "quantity": {
        "amount": 3,
        "unit": "dash"
      }
    },
    {
      "name": "Pernod",
      "type": "spirit",
      "quantity": {
        "amount": 3,
        "unit": "dash"
      }
    },
    {
      "name": "lime juice",
      "type": "juice",
      "quantity": {
        "amount": 0.5,
        "unit": "oz"
      }
    },
    {
      "name": "orange juice",
      "type": "juice",
      "quantity": {
        "amount": 0.5,
        "unit": "oz"
      }
    },
    {
      "name": "passionola",
      "type": "syrup",
      "quantity": {
        "amount": 0.5,
        "unit": "oz"
      }
    },
    {
      "name": "Column still lightly aged rum",
      "type": "category",
      "quantity": {
        "amount": 0.5,
        "unit": "oz"
      }
    },
    {
      "name": "Black Blended Rum (Jamaica)",
      "type": "category",
      "quantity": {
        "amount": 1,
        "unit": "oz"
      }
    }
  ],
  "preparation": "flash blended",
  "served_on": "crushed ice",
  "glassware": "footed pilsner",
  "attributions": [
    {
      "source": "Mr. Lemon Hart's Tropical Treat booklet",
      "relation": "book"
    }
  ],
  "refs": [
    {
      "type": "youtube",
      "videoId": "bIYy6RP76CQ"
    }
  ]
}
