{
  "$schema": "../../../../../schemas/recipe.schema.json",
  "name": "Bali Hai Bastard",
  "glassware": "old fashioned",
  "preparation": "shaken",
  "served_on": "crushed ice",
  "ingredients": [
    {
      "name": "lime juice",
      "type": "juice",
      "quantity": {
        "amount": 0.75,
        "unit": "oz"
      }
    },
    {
      "name": "pineapple juice",
      "type": "juice",
      "quantity": {
        "amount": 1.5,
        "unit": "oz"
      }
    },
    {
      "name": "demerara syrup",
      "type": "syrup",
      "quantity": {
        "amount": 0.5,
        "unit": "oz"
      }
    },
    {
      "name": "passion fruit purée",
      "type": "puree",
      "quantity": {
        "amount": 0.5,
        "unit": "oz"
      }
    },
    {
      "name": "Cutwater Bali Hai Tiki Gold Pineapple Rum",
      "type": "spirit",
      "quantity": {
        "amount": 1.5,
        "unit": "oz"
      }
    },
    {
      "name": "La Luna Mezcal",
      "type": "spirit",
      "quantity": {
        "amount": 0.25,
        "unit": "oz"
      }
    },
    {
      "name": "Rittenhouse Rye",
      "type": "spirit",
      "quantity": {
        "amount": 0.75,
        "unit": "oz"
      }
    }
  ],
  "instructions": [
    "Build ingredients in shaker.",
    "Shake with cubed ice, strain into a double old-fashioned glass.",
    "Fill with fresh crushed ice.",
    "Garnish with two pineapple fronds and a pineapple wedge."
  ],
  "attributions": [
    {
      "relation": "recipe author",
      "source": "Marie King"
    }
  ],
  "refs": [
    {
      "type": "book",
      "title": "Minimalist Tiki",
      "page": 190
    }
  ]
}
