{
  "$schema": "../../../../../schemas/recipe.schema.json",
  "name": "Davy Jones",
  "preparation": "shaken",
  "served_on": "crushed ice",
  "glassware": "collins",
  "ingredients": [
    {
      "name": "Peychaud's bitters",
      "type": "bitter",
      "quantity": {
        "amount": 3,
        "unit": "dash"
      }
    },
    {
      "name": "Lemon juice",
      "type": "juice",
      "quantity": {
        "amount": 1,
        "unit": "oz"
      }
    },
    {
      "name": "Orgeat",
      "type": "category",
      "quantity": {
        "amount": 1,
        "unit": "oz"
      }
    },
    {
      "name": "Orange Curaçao",
      "type": "category",
      "quantity": {
        "amount": 0.25,
        "unit": "oz"
      }
    },
    {
      "name": "Sipsmith Gin",
      "type": "spirit",
      "quantity": {
        "amount": 1,
        "unit": "oz"
      }
    }
  ],
  "instructions": [
    "Garnish with the bitters, a lemon zest twist, and a long swizzle stick."
  ],
  "attributions": [
    {
      "relation": "recipe author",
      "source": "Tiki Lindy"
    }
  ],
  "refs": [
    {
      "type": "book",
      "title": "Minimalist Tiki",
      "page": 206
    }
  ]
}
