{
  "$schema": "../../../../../schemas/recipe.schema.json",
  "name": "Primrose",
  "preparation": "stirred",
  "served_on": "big rock",
  "glassware": "old fashioned",
  "ingredients": [
    {
      "name": "House Orange Bitters",
      "type": "bitter",
      "quantity": {
        "amount": 1,
        "unit": "dash"
      }
    },
    {
      "name": "Simple syrup",
      "type": "syrup",
      "quantity": {
        "amount": 1,
        "unit": "tsp"
      }
    },
    {
      "name": "Del Maguey Santo Domingo Albarradas Mezcal",
      "type": "spirit",
      "quantity": {
        "amount": 0.5,
        "unit": "oz"
      }
    },
    {
      "name": "Italicus",
      "type": "liqueur",
      "quantity": {
        "amount": 0.5,
        "unit": "oz"
      }
    },
    {
      "name": "Domaine d'Espérance Blanche Armagnac",
      "type": "spirit",
      "quantity": {
        "amount": 1.5,
        "unit": "oz"
      }
    }
  ],
  "instructions": ["Express the lemon twist over the drink, then place it in the drink."],
  "attributions": [
    {
      "relation": "recipe author",
      "source": "Jarred Weigand"
    },
    {
      "relation": "bar",
      "source": "Death & Co",
      "location": "New York, NY"
    }
  ],
  "refs": [
    {
      "type": "book",
      "title": "death-co-welcome-home",
      "page": 241
    }
  ]
}
