{
  "$schema": "../../../../../schemas/recipe.schema.json",
  "name": "Warspite",
  "preparation": "stirred",
  "served_on": "big rock",
  "glassware": "old fashioned",
  "ingredients": [
    {
      "name": "St-Elizabeth Allspice Dram",
      "type": "liqueur",
      "quantity": {
        "amount": 1,
        "unit": "tsp"
      }
    },
    {
      "name": "Clear Creek Blue Plum Brandy",
      "type": "spirit",
      "quantity": {
        "amount": 0.25,
        "unit": "oz"
      }
    },
    {
      "name": "Plymouth Sloe Gin",
      "type": "liqueur",
      "quantity": {
        "amount": 0.5,
        "unit": "oz"
      }
    },
    {
      "name": "Aperol",
      "type": "liqueur",
      "quantity": {
        "amount": 0.75,
        "unit": "oz"
      }
    },
    {
      "name": "Plymouth Gin",
      "type": "spirit",
      "quantity": {
        "amount": 1.25,
        "unit": "oz"
      }
    }
  ],
  "instructions": [
    "Express the orange twist over the drink, then place it in the drink."
  ],
  "attributions": [
    {
      "relation": "recipe author",
      "source": "Matthew Belanger"
    },
    {
      "relation": "bar",
      "source": "Death & Co",
      "location": "New York, NY"
    }
  ],
  "refs": [
    {
      "type": "book",
      "title": "death-co-welcome-home",
      "page": 245
    }
  ]
}
