{
  "$schema": "../../../../schemas/recipe.schema.json",
  "name": "Mean Fiddler",
  "preparation": "stirred",
  "served_on": "up",
  "glassware": "nick & nora",
  "ingredients": [
    {
      "name": "Angostura bitters",
      "type": "bitter",
      "quantity": {
        "amount": 2,
        "unit": "dash"
      }
    },
    {
      "name": "Cinnamon syrup",
      "type": "syrup",
      "quantity": {
        "amount": 1,
        "unit": "tsp"
      }
    },
    {
      "name": "Campari",
      "type": "liqueur",
      "quantity": {
        "amount": 0.5,
        "unit": "oz"
      }
    },
    {
      "name": "Cocchi Vermouth di Torino",
      "type": "wine",
      "quantity": {
        "amount": 0.75,
        "unit": "oz"
      }
    },
    {
      "name": "Green Chartreuse",
      "type": "liqueur",
      "quantity": {
        "amount": 0.75,
        "unit": "oz"
      }
    },
    {
      "name": "Laphroaig 10",
      "type": "spirit",
      "quantity": {
        "amount": 0.5,
        "unit": "oz"
      }
    },
    {
      "name": "Redbreast 12 year Irish whiskey",
      "type": "spirit",
      "quantity": {
        "amount": 1,
        "unit": "oz"
      }
    }
  ],
  "instructions": [
    "Combine all ingredients in a mixing glass with ice.",
    "Stir until chilled.",
    "Strain into a Nick & Nora glass.",
    "Express a lemon peel over the glass and use as garnish."
  ],
  "refs": [
    {
      "type": "youtube",
      "videoId": "wPsvBjSjpCg",
      "start": 247
    }
  ]
}
