{
  "$schema": "../../../schemas/recipe.schema.json",
  "name": "Kang the Conqueror",
  "preparation": "stirred",
  "served_on": "big rock",
  "glassware": "old fashioned",
  "ingredients": [
    {
      "name": "Simple syrup",
      "type": "syrup",
      "quantity": {
        "amount": 0.5,
        "unit": "oz"
      }
    },
    {
      "name": "Lemon juice",
      "type": "juice",
      "quantity": {
        "amount": 1,
        "unit": "oz"
      }
    },
    {
      "name": "Empress 1908 Gin",
      "type": "spirit",
      "quantity": {
        "amount": 2,
        "unit": "oz"
      }
    },
    {
      "name": "Amaro Averna",
      "type": "liqueur",
      "technique": [
        {
          "technique": "gelification",
          "agent": "210s",
          "concentration": "1/2 tsp"
        },
        {
          "technique": "application",
          "method": "float"
        }
      ],
      "quantity": {
        "amount": 0.5,
        "unit": "oz"
      }
    }
  ],
  "refs": [
    {
      "type": "youtube",
      "videoId": "BXdM4Cin9io"
    }
  ]
}
