{
  "$schema": "../../../schemas/recipe.schema.json",
  "name": "Shark's Tooth",
  "preparation": "flash blended",
  "served_on": "crushed ice",
  "glassware": "tiki",
  "ingredients": [
    {
      "name": "Lime juice",
      "type": "juice",
      "quantity": {
        "amount": 0.5,
        "unit": "oz"
      }
    },
    {
      "name": "Pineapple juice",
      "type": "juice",
      "quantity": {
        "amount": 0.5,
        "unit": "oz"
      }
    },
    {
      "name": "cherry syrup",
      "type": "syrup",
      "brix": 50,
      "quantity": {
        "amount": 0.5,
        "unit": "oz"
      }
    },
    {
      "name": "Mount Gay Black Barrel",
      "type": "spirit",
      "quantity": {
        "amount": 1,
        "unit": "oz"
      }
    },
    {
      "name": "Coruba",
      "type": "spirit",
      "quantity": {
        "amount": 1,
        "unit": "oz"
      }
    }
  ],
  "instructions": [
    "Serve in a glass with a ice shell.",
    "The cherry syrup can be substituted with 1/2oz of simply syrup + a barspoon of maraschino cherry syrup. Or simply with grenadine."
  ],
  "attributions": [
    {
      "relation": "recipe author",
      "source": "Don the Beachcomber"
    }
  ],
  "refs": [
    {
      "type": "youtube",
      "videoId": "pbP779rw-A4"
    }
  ]
}
