{
  "$schema": "../../../../../schemas/recipe.schema.json",
  "name": "Game Loves Game",
  "preparation": "shaken",
  "served_on": "crushed ice",
  "glassware": "collins",
  "ingredients": [
    {
      "name": "Cucumber",
      "type": "fruit",
      "technique": [
        {
          "technique": "muddled"
        }
      ],
      "quantity": {
        "amount": 2,
        "unit": "unit"
      }
    },
    {
      "name": "rose water",
      "type": "other",
      "quantity": {
        "amount": 1,
        "unit": "drop"
      }
    },
    {
      "name": "Honey syrup",
      "type": "syrup",
      "quantity": {
        "amount": 0.5,
        "unit": "oz"
      }
    },
    {
      "name": "Bonal Gentiane-Quina",
      "type": "wine",
      "quantity": {
        "amount": 0.25,
        "unit": "oz"
      }
    },
    {
      "name": "Green Chartreuse",
      "type": "liqueur",
      "quantity": {
        "amount": 0.25,
        "unit": "oz"
      }
    },
    {
      "name": "Dolin Dry Vermouth de Chambéry",
      "type": "wine",
      "quantity": {
        "amount": 0.5,
        "unit": "oz"
      }
    },
    {
      "name": "Perry's Tot Navy Strength Gin",
      "type": "spirit",
      "quantity": {
        "amount": 1,
        "unit": "oz"
      }
    },
    {
      "name": "Dry white wine",
      "type": "category",
      "quantity": {
        "amount": 1,
        "unit": "oz"
      }
    }
  ],
  "instructions": [
    "In a shaker, gently muddle the cucumber slices. Add the remaining ingredients and shake with ice. Double strain into a collins glass and fill the glass with crushed ice. Garnish with the cucumber ribbon."
  ],
  "attributions": [
    {
      "relation": "recipe author",
      "source": "AJ Stocak"
    },
    {
      "relation": "bar",
      "source": "Death & Co"
    }
  ],
  "refs": [
    {
      "type": "book",
      "title": "death-co-welcome-home",
      "page": 253
    }
  ]
}
