{
  "$schema": "../../../../../schemas/recipe.schema.json",
  "name": "Tiger Tanaka",
  "preparation": "stirred",
  "served_on": "up",
  "glassware": "nick & nora",
  "ingredients": [
    {
      "name": "green shiso leaves",
      "type": "other",
      "quantity": {
        "amount": 1,
        "unit": "unit"
      }
    },
    {
      "name": "Green Chartreuse",
      "type": "liqueur",
      "quantity": {
        "amount": 0.25,
        "unit": "oz"
      }
    },
    {
      "name": "Noilly Prat Extra Dry Vermouth",
      "type": "wine",
      "quantity": {
        "amount": 1,
        "unit": "oz"
      }
    },
    {
      "name": "Monkey 47 Schwarzwald Dry Gin",
      "type": "spirit",
      "quantity": {
        "amount": 1,
        "unit": "oz"
      }
    },
    {
      "name": "Siembra Valles Blanco",
      "type": "spirit",
      "quantity": {
        "amount": 1,
        "unit": "oz"
      }
    }
  ],
  "instructions": [
    "Stir all the ingredients over ice, then strain into a chilled Nick & Nora glass. Garnish with the shiso leaf."
  ],
  "attributions": [
    {
      "relation": "recipe author",
      "source": "Matthew Belanger"
    },
    {
      "relation": "bar",
      "source": "Death & Co"
    }
  ],
  "refs": [
    {
      "type": "book",
      "title": "death-co-welcome-home",
      "page": 268
    }
  ]
}
